{
  "questions": [
    {
      "id": 1,
      "questionLabel": "What is a component in Angular?",
      "categoryId": 1
    },
    {
      "id": 2,
      "questionLabel": "Explain the purpose of the NgModule in Angular.",
      "categoryId": 1
    },
    {
      "id": 3,
      "questionLabel": "How do you create a new Angular application?",
      "categoryId": 1
    },
    {
      "id": 4,
      "questionLabel": "What is data binding in Angular, and what are the different types of data binding?",
      "categoryId": 1
    },
    {
      "id": 5,
      "questionLabel": "Explain the difference between {{}} (interpolation) and [property] (property binding) in Angular templates.",
      "categoryId": 1
    },
    {
      "id": 6,
      "questionLabel": "Explain the concept of polymorphism in Object-Oriented Programming?",
      "categoryId": 2
    },
    {
      "id": 7,
      "questionLabel": "Describe the purpose of the JVM in the Java ecosystem.?",
      "categoryId": 2
    },
    {
      "id": 8,
      "questionLabel": "What is a Java Interface, and how does it differ from an abstract class?",
      "categoryId": 2
    },
    {
      "id": 9,
      "questionLabel": "What are Java annotations, and how are they used in frameworks like Spring?",
      "categoryId": 2
    },
    {
      "id": 10,
      "questionLabel": "Explain the difference between checked and unchecked exceptions in Java?",
      "categoryId": 2
    },
    {
      "id": 11,
      "questionLabel": "What is the box model in CSS, and how does it affect layout?",
      "categoryId": 3
    },
    {
      "id": 12,
      "questionLabel": "Explain the difference between `inline`, `block`, and `inline-block` elements in CSS",
      "categoryId": 3
    },
    {
      "id": 13,
      "questionLabel": "How does CSS Flexbox work, and when should it be used?",
      "categoryId": 3
    },
    {
      "id": 14,
      "questionLabel": "Explain the concept of modules in Angular and their role in organizing an application.",
      "categoryId": 3
    },
    {
      "id": 15,
      "questionLabel": "What are CSS media queries, and how do they enable responsive design?",
      "categoryId": 3
    }
  ],
  "answers": [
    {
      "questionId": 1,
      "answerLabel": "A reusable building block for the user interface",
      "isCorrect": true
    },
    {
      "questionId": 1,
      "answerLabel": "A style in Angular",
      "isCorrect": false
    },
    {
      "questionId": 1,
      "answerLabel": "A service for handling HTTP requests",
      "isCorrect": false
    },
    {
      "questionId": 1,
      "answerLabel": "A routing configuration",
      "isCorrect": false
    },
    {
      "questionId": 2,
      "answerLabel": "NgModule is used to declare and configure modules in Angular applications.",
      "isCorrect": true
    },
    {
      "questionId": 2,
      "answerLabel": "NgModule is a component in Angular.",
      "isCorrect": false
    },
    {
      "questionId": 2,
      "answerLabel": "NgModule is used for data binding in Angular.",
      "isCorrect": false
    },
    {
      "questionId": 2,
      "answerLabel": "NgModule is a directive in Angular.",
      "isCorrect": false
    },
    {
      "questionId": 3,
      "answerLabel": "You can create a new Angular application using the Angular CLI by running 'ng new app-name'.",
      "isCorrect": true
    },
    {
      "questionId": 3,
      "answerLabel": "You can create a new Angular application by writing HTML and CSS files.",
      "isCorrect": false
    },
    {
      "questionId": 3,
      "answerLabel": "You can create a new Angular application using pure JavaScript.",
      "isCorrect": false
    },
    {
      "questionId": 3,
      "answerLabel": "You can create a new Angular application using Python.",
      "isCorrect": false
    },
    {
      "questionId": 4,
      "answerLabel": "Data binding in Angular is a mechanism for synchronizing data between the component and the view.",
      "isCorrect": true
    },
    {
      "questionId": 4,
      "answerLabel": "Data binding in Angular is used for creating components.",
      "isCorrect": false
    },
    {
      "questionId": 4,
      "answerLabel": "Data binding in Angular is a routing feature.",
      "isCorrect": false
    },
    {
      "questionId": 4,
      "answerLabel": "Data binding in Angular is only available for services.",
      "isCorrect": false
    },
    {
      "questionId": 5,
      "answerLabel": "{{}} (interpolation) is used for displaying dynamic data in the template.",
      "isCorrect": true
    },
    {
      "questionId": 5,
      "answerLabel": "[property] (property binding) is used for displaying dynamic data in the template.",
      "isCorrect": false
    },
    {
      "questionId": 5,
      "answerLabel": "{{}} (interpolation) is used for creating CSS styles.",
      "isCorrect": false
    },
    {
      "questionId": 5,
      "answerLabel": "[property] (property binding) is used for creating services.",
      "isCorrect": false
    },
    {
      "questionId": 6,
      "answerLabel": "Event event.",
      "isCorrect": true
    },
    {
      "questionId": 6,
      "answerLabel": "Event binding  styles.",
      "isCorrect": false
    },
    {
      "questionId": 6,
      "answerLabel": "Event CSS.",
      "isCorrect": false
    },
    {
      "questionId": 6,
      "answerLabel": "Event binding in Angular is used for dependency injection.",
      "isCorrect": false
    },
    {
      "questionId": 7,
      "answerLabel": "Angular CLI (Command Line Interface) is a command-line tool for creating, building, and deploying Angular applications.",
      "isCorrect": true
    },
    {
      "questionId": 7,
      "answerLabel": "Angular CLI is a component in Angular applications.",
      "isCorrect": false
    },
    {
      "questionId": 7,
      "answerLabel": "Angular CLI is a directive in Angular applications.",
      "isCorrect": false
    },
    {
      "questionId": 7,
      "answerLabel": "Angular CLI is a service for handling HTTP requests.",
      "isCorrect": false
    },
    {
      "questionId": 8,
      "answerLabel": "A directive in Angular is a marker on a DOM element that tells Angular to do something with that element.",
      "isCorrect": true
    },
    {
      "questionId": 8,
      "answerLabel": "A directive in Angular is a component.",
      "isCorrect": false
    },
    {
      "questionId": 8,
      "answerLabel": "A directive in Angular is a service.",
      "isCorrect": false
    },
    {
      "questionId": 8,
      "answerLabel": "A directive in Angular is a module.",
      "isCorrect": false
    },
    {
      "questionId": 9,
      "answerLabel": "The Angular router is a library for navigating between views and components.",
      "isCorrect": true
    },
    {
      "questionId": 9,
      "answerLabel": "The Angular router is used for handling HTTP requests.",
      "isCorrect": false
    },
    {
      "questionId": 9,
      "answerLabel": "The Angular router is used for data binding in Angular.",
      "isCorrect": false
    },
    {
      "questionId": 9,
      "answerLabel": "The Angular router is used for event binding in Angular.",
      "isCorrect": false
    },
    {
      "questionId": 10,
      "answerLabel": "Flexbox is a layout model that allows for responsive design by distributing space dynamically among items in a container",
      "isCorrect": true
    },
    {
      "questionId": 10,
      "answerLabel": "It provides an efficient way to align and distribute space among items in a container, especially when the size of items",
      "isCorrect": false
    },
    {
      "questionId": 10,
      "answerLabel": "Dependency injection in Angular is a way to create routes in an application.",
      "isCorrect": false
    },
    {
      "questionId": 10,
      "answerLabel": "Dependency injection in Angular is used for data binding.",
      "isCorrect": false
    },
    {
      "questionId": 11,
      "answerLabel": "Communication between parent and child components in Angular can be achieved through input properties and output events.",
      "isCorrect": true
    },
    {
      "questionId": 11,
      "answerLabel": "Communication between parent and child components in Angular is not possible.",
      "isCorrect": false
    },
    {
      "questionId": 11,
      "answerLabel": "Communication between parent and child components in Angular can only be done using services.",
      "isCorrect": false
    },
    {
      "questionId": 11,
      "answerLabel": "Communication between parent and child components in Angular can only be done using event binding.",
      "isCorrect": false
    },
    {
      "questionId": 12,
      "answerLabel": "A service in Angular is a class that provides specific functionality and can be injected into components and other services.",
      "isCorrect": true
    },
    {
      "questionId": 12,
      "answerLabel": "A service in Angular is a type of component.",
      "isCorrect": false
    },
    {
      "questionId": 12,
      "answerLabel": "A service in Angular is a type of directive.",
      "isCorrect": false
    },
    {
      "questionId": 12,
      "answerLabel": "A service in Angular is a type of module.",
      "isCorrect": false
    },
    {
      "questionId": 13,
      "answerLabel": "The ngFor directive in Angular is used for iterating over a list of items and rendering them in the template.",
      "isCorrect": true
    },
    {
      "questionId": 13,
      "answerLabel": "The ngFor directive in Angular is used for defining routes.",
      "isCorrect": false
    },
    {
      "questionId": 13,
      "answerLabel": "The ngFor directive in Angular is used for handling HTTP requests.",
      "isCorrect": false
    },
    {
      "questionId": 13,
      "answerLabel": "The ngFor directive in Angular is used for event binding.",
      "isCorrect": false
    },
    {
      "questionId": 14,
      "answerLabel": "Modules in Angular are used to organize the application into cohesive blocks of functionality.",
      "isCorrect": true
    },
    {
      "questionId": 14,
      "answerLabel": "Modules in Angular are used for data binding.",
      "isCorrect": false
    },
    {
      "questionId": 14,
      "answerLabel": "Modules in Angular are used for routing configuration.",
      "isCorrect": false
    },
    {
      "questionId": 14,
      "answerLabel": "Modules in Angular are used for handling HTTP requests.",
      "isCorrect": false
    },
    {
      "questionId": 15,
      "answerLabel": "Angular CLI's 'ng serve' command is used to compile and serve an Angular application locally for development purposes.",
      "isCorrect": true
    },
    {
      "questionId": 15,
      "answerLabel": "The CSS Grid allows for precise control over the placement of elements in both horizontal and vertical spaces.",
      "isCorrect": false
    },
    {
      "questionId": 15,
      "answerLabel": "Grid is ideal for creating complex, grid-based layouts where control over both dimensions is required, whereas Flexbox is better suited for simpler, one-dimensional layouts.",
      "isCorrect": false
    },
    {
      "questionId": 15,
      "answerLabel": "CSS Grid is a two-dimensional layout system that controls both rows and columns.",
      "isCorrect": false
    }
  ],
  "users": [
    {
      "id": 1,
      "username": "admin",
      "password": "admin"
    },
    {
      "id": 2,
      "username": "user",
      "password": "user"
    }
  ],
  "categories": [
    {
      "id":1,
      "name": "ANGULAR"
    },
    {
      "id":2,
      "name": "JAVA"
    },
    {
      "id":3,
      "name": "CSS"
    }

  ]


}
